LICENSE
README.md
setup.cfg
setup.py
r3build/__init__.py
r3build/__main__.py
r3build/cli.py
r3build/cli_test.py
r3build/config.py
r3build/config_class.py
r3build/config_test.py
r3build/config_validator.py
r3build/function_test.py
r3build/processor.py
r3build/prompter.py
r3build/watcher.py
r3build.egg-info/PKG-INFO
r3build.egg-info/SOURCES.txt
r3build.egg-info/dependency_links.txt
r3build.egg-info/entry_points.txt
r3build.egg-info/requires.txt
r3build.egg-info/top_level.txt