Metadata-Version: 2.1
Name: r3build
Version: 0.10.0
Summary: A smart file watcher with an easy but powerful configuration.
Home-page: https://github.com/puhitaku/r3build
Author: Takumi Sueda
Author-email: puhitaku@gmail.com
License: UNKNOWN
Platform: UNKNOWN
Classifier: Development Status :: 4 - Beta
Classifier: License :: OSI Approved :: MIT License
Classifier: Programming Language :: Python :: 3
Classifier: Programming Language :: Python :: 3.7
Classifier: Programming Language :: Python :: 3.8
Classifier: Programming Language :: Python :: 3.9
Classifier: Topic :: Utilities
Requires-Python: >=3.6
